[
    {
        "key": "nde.app.root.title",
        "locale": "nl-NL",
        "value": "App"
    },
    {
        "key": "nde.root.alerts.error",
        "locale": "nl-NL",
        "value": "Er ging iets fout"
    },
    {
        "key": "nde.collections.alerts.created-collection",
        "locale": "nl-NL",
        "value": "Collectie aangemaakt"
    },
    {
        "key": "nde.navigation.search.title",
        "locale": "nl-NL",
        "value": "Zoeken"
    },
    {
        "key": "nde.navigation.collections.title",
        "locale": "nl-NL",
        "value": "Collecties"
    },
    {
        "key": "nde.collections.card.name-unavailable",
        "locale": "nl-NL",
        "value": "Naam onbekend"
    },
    {
        "key": "nde.collections.card.subject-unavailable",
        "locale": "nl-NL",
        "value": "Onderwerp onbekend"
    },
    {
        "key": "nde.features.collections.root.empty.create-object-title",
        "locale": "nl-NL",
        "value": "Maak je eerste object aan"
    },
    {
        "key": "nde.features.collections.root.empty.create-object-button",
        "locale": "nl-NL",
        "value": "Object aanmaken"
    },
    {
        "key": "nde.features.authenticate.error.invalid-webid.no-webid",
        "locale": "nl-NL",
        "value": "Gelieve een WebID in te voeren."
    },
    {
        "key": "nde.features.authenticate.error.invalid-webid.invalid-url",
        "locale": "nl-NL",
        "value": "Gelieve een geldig WebID in te voeren."
    },
    {
        "key": "nde.features.authenticate.error.invalid-webid.no-profile",
        "locale": "nl-NL",
        "value": "Er werd geen actieve profielpagina gevonden voor deze WebID."
    },
    {
        "key": "nde.features.authenticate.error.invalid-webid.no-oidc-registration",
        "locale": "nl-NL",
        "value": "De opgegeven WebID is nog niet gelinkt aan een OIDC-provider. Meer info hierover vind je bij de FAQ."
    },
    {
        "key": "nde.features.authenticate.error.invalid-webid.invalid-oidc-registration",
        "locale": "nl-NL",
        "value": "De opgegeven WebID is gelinkt aan een foutieve OIDC-provider. Meer info hierover vind je bij de FAQ."
    },
    {
        "key": "nde.features.authenticate.pages.login.title",
        "locale": "nl-NL",
        "value": "Collectiebeheersysteem"
    },
    {
        "key": "nde.features.authenticate.pages.login.webid-placeholder",
        "locale": "nl-NL",
        "value": "bv. https://profile.janjanssens.nl/"
    },
    {
        "key": "nde.features.authenticate.pages.login.webid-label",
        "locale": "nl-NL",
        "value": "WebID"
    },
    {
        "key": "nde.features.authenticate.pages.login.create-webid",
        "locale": "nl-NL",
        "value": "Nog geen WebID? Klik <a href=\"https://pods.nde.nl\">hier</a>."
    },
    {
        "key": "nde.features.collections.alerts.created-collection",
        "locale": "nl-NL",
        "value": "Collectie aangemaakt"
    },
    {
        "key": "nde.features.collections.root.title",
        "locale": "nl-NL",
        "value": "Collecties"
    },
    {
        "key": "nde.features.collections.card.name-unavailable",
        "locale": "nl-NL",
        "value": "Naam onbekend"
    },
    {
        "key": "nde.features.collections.card.subject-unavailable",
        "locale": "nl-NL",
        "value": "Onderwerp onbekend"
    },
    {
        "key": "nde.features.collections.new-collection-name",
        "locale": "nl-NL",
        "value": "Nieuwe collectie"
    },
    {
        "key": "nde.features.collections.new-collection-description",
        "locale": "nl-NL",
        "value": "Beschrijving van deze collectie"
    },
    {
        "key": "nde.features.search.header.search-results-for",
        "locale": "nl-NL",
        "value": "Zoekresultaten voor"
    },
    {
        "key": "nde.features.search.header.subtitle",
        "locale": "nl-NL",
        "value": "We hebben dit gevonden"
    },
    {
        "key": "nde.features.search.root.empty.no-search-results",
        "locale": "nl-NL",
        "value": "Geen zoekresultaten voor deze zoekterm!"
    },
    {
        "key": "nde.features.search.root.empty.go-back",
        "locale": "nl-NL",
        "value": "Ga terug"
    },
    {
        "key": "nde.features.search.root.objects",
        "locale": "nl-NL",
        "value": "Objecten"
    },
    {
        "key": "nde.features.search.root.collections",
        "locale": "nl-NL",
        "value": "Collecties"
    },
    {
        "key": "nde.features.object.new-object-name",
        "locale": "nl-NL",
        "value": "Nieuw object"
    },
    {
        "key": "nde.features.object.new-object-description",
        "locale": "nl-NL",
        "value": "Beschrijving van dit object"
    },
    {
        "key": "nde.features.object.sidebar.title",
        "locale": "nl-NL",
        "value": "Onderdelen"
    },
    {
        "key": "nde.features.object.sidebar.image",
        "locale": "nl-NL",
        "value": "Beeldmateriaal"
    },
    {
        "key": "nde.features.object.sidebar.identification",
        "locale": "nl-NL",
        "value": "Identificatie"
    },
    {
        "key": "nde.features.object.sidebar.representation",
        "locale": "nl-NL",
        "value": "Voorstelling"
    },
    {
        "key": "nde.features.object.sidebar.creation",
        "locale": "nl-NL",
        "value": "Vervaardiging"
    },
    {
        "key": "nde.features.object.sidebar.dimensions",
        "locale": "nl-NL",
        "value": "Afmetingen"
    },
    {
        "key": "nde.features.object.sidebar.other",
        "locale": "nl-NL",
        "value": "Overige"
    },
    {
        "key": "nde.features.object.card.common.empty",
        "locale": "nl-NL",
        "value": "Dit veld is verplicht."
    },
    {
        "key": "nde.features.object.card.image.title",
        "locale": "nl-NL",
        "value": "Beeldmateriaal"
    },
    {
        "key": "nde.features.object.card.image.subtitle",
        "locale": "nl-NL",
        "value": "Het beeldmateriaal van dit object."
    },
    {
        "key": "nde.features.object.card.image.field.file",
        "locale": "nl-NL",
        "value": "Bestand"
    },
    {
        "key": "nde.features.object.card.image.field.file.validation.invalid",
        "locale": "nl-NL",
        "value": "De ingegeven URL is niet geldig."
    },
    {
        "key": "nde.features.object.card.image.field.license",
        "locale": "nl-NL",
        "value": "Licentie"
    },
    {
        "key": "nde.features.object.card.identification.title",
        "locale": "nl-NL",
        "value": "Identificatie"
    },
    {
        "key": "nde.features.object.card.identification.subtitle",
        "locale": "nl-NL",
        "value": "De identificatie van dit object."
    },
    {
        "key": "nde.features.object.card.identification.field.object-number",
        "locale": "nl-NL",
        "value": "Objectnummer"
    },
    {
        "key": "nde.features.object.card.identification.field.object-name",
        "locale": "nl-NL",
        "value": "Objectnaam"
    },
    {
        "key": "nde.features.object.card.identification.field.type",
        "locale": "nl-NL",
        "value": "Type"
    },
    {
        "key": "nde.features.object.card.identification.field.title",
        "locale": "nl-NL",
        "value": "Titel"
    },
    {
        "key": "nde.features.object.card.identification.field.description",
        "locale": "nl-NL",
        "value": "Korte beschrijving"
    },
    {
        "key": "nde.features.object.card.identification.field.description.validation.max-characters",
        "locale": "nl-NL",
        "value": "De beschrijving mag maximum 10000 karakters lang zijn!"
    },
    {
        "key": "nde.features.object.card.identification.field.collection",
        "locale": "nl-NL",
        "value": "Collectie"
    },
    {
        "key": "nde.features.object.card.creation.title",
        "locale": "nl-NL",
        "value": "Vervaardiging"
    },
    {
        "key": "nde.features.object.card.creation.subtitle",
        "locale": "nl-NL",
        "value": "De vervaardiging van dit object."
    },
    {
        "key": "nde.features.object.card.creation.field.creator",
        "locale": "nl-NL",
        "value": "Vervaardiger"
    },
    {
        "key": "nde.features.object.card.creation.field.location",
        "locale": "nl-NL",
        "value": "Plaats"
    },
    {
        "key": "nde.features.object.card.creation.field.material",
        "locale": "nl-NL",
        "value": "Materiaal"
    },
    {
        "key": "nde.features.object.card.creation.field.date",
        "locale": "nl-NL",
        "value": "Datum"
    },
    {
        "key": "nde.features.object.card.creation.field.date.validation.invalid",
        "locale": "nl-NL",
        "value": "De ingegeven datum is niet geldig."
    },
    {
        "key": "nde.features.object.card.representation.title",
        "locale": "nl-NL",
        "value": "Voorstelling"
    },
    {
        "key": "nde.features.object.card.representation.subtitle",
        "locale": "nl-NL",
        "value": "De voorstelling van dit object."
    },
    {
        "key": "nde.features.object.card.representation.field.subject",
        "locale": "nl-NL",
        "value": "Onderwerp"
    },
    {
        "key": "nde.features.object.card.representation.field.location",
        "locale": "nl-NL",
        "value": "Locatie"
    },
    {
        "key": "nde.features.object.card.representation.field.person",
        "locale": "nl-NL",
        "value": "Persoon"
    },
    {
        "key": "nde.features.object.card.representation.field.organization",
        "locale": "nl-NL",
        "value": "Organisatie"
    },
    {
        "key": "nde.features.object.card.representation.field.event",
        "locale": "nl-NL",
        "value": "Gebeurtenis"
    },
    {
        "key": "nde.features.object.card.dimensions.title",
        "locale": "nl-NL",
        "value": "Afmetingen"
    },
    {
        "key": "nde.features.object.card.dimensions.subtitle",
        "locale": "nl-NL",
        "value": "De afmetingen van dit object."
    },
    {
        "key": "nde.features.object.card.dimensions.field.depth",
        "locale": "nl-NL",
        "value": "Diepte"
    },
    {
        "key": "nde.features.object.card.dimensions.field.width",
        "locale": "nl-NL",
        "value": "Breedte"
    },
    {
        "key": "nde.features.object.card.dimensions.field.height",
        "locale": "nl-NL",
        "value": "Hoogte"
    },
    {
        "key": "nde.features.object.card.dimensions.field.weight",
        "locale": "nl-NL",
        "value": "Gewicht"
    },
    {
        "key": "nde.common.date.just-now",
        "locale": "nl-NL",
        "value": "enkele ogenblikken geleden"
    },
    {
        "key": "nde.common.date.minutes-ago",
        "locale": "nl-NL",
        "value": "minuten geleden"
    },
    {
        "key": "nde.common.date.hour-ago",
        "locale": "nl-NL",
        "value": "uur geleden"
    },
    {
        "key": "nde.common.date.hours-ago",
        "locale": "nl-NL",
        "value": "uur geleden"
    },
    {
        "key": "nde.common.date.day-ago",
        "locale": "nl-NL",
        "value": "dag geleden"
    },
    {
        "key": "nde.common.date.days-ago",
        "locale": "nl-NL",
        "value": "dagen geleden"
    },
    {
        "key": "nde.common.date.month-ago",
        "locale": "nl-NL",
        "value": "maand geleden"
    },
    {
        "key": "nde.common.date.months-ago",
        "locale": "nl-NL",
        "value": "maanden geleden"
    },
    {
        "key": "nde.common.date.year-ago",
        "locale": "nl-NL",
        "value": "jaar geleden"
    },
    {
        "key": "nde.common.date.years-ago",
        "locale": "nl-NL",
        "value": "jaar geleden"
    }
]
